coolest/__init__.py
coolest/api/__init__.py
coolest/api/analysis.py
coolest/api/composable_models.py
coolest/api/coordinates.py
coolest/api/plot_util.py
coolest/api/plotting.py
coolest/api/util.py
coolest/api/profiles/__init__.py
coolest/api/profiles/light.py
coolest/api/profiles/mass.py
coolest/api/profiles/util.py
coolest/template/__init__.py
coolest/template/info.py
coolest/template/json.py
coolest/template/lazy.py
coolest/template/standard.py
coolest/template/classes/__init__.py
coolest/template/classes/base.py
coolest/template/classes/coordinates.py
coolest/template/classes/cosmology.py
coolest/template/classes/fits_file.py
coolest/template/classes/galaxy.py
coolest/template/classes/grid.py
coolest/template/classes/instrument.py
coolest/template/classes/lensing_entity.py
coolest/template/classes/lensing_entity_list.py
coolest/template/classes/likelihood.py
coolest/template/classes/likelihood_list.py
coolest/template/classes/mass_field.py
coolest/template/classes/mass_light_model.py
coolest/template/classes/noise.py
coolest/template/classes/observation.py
coolest/template/classes/parameter.py
coolest/template/classes/probabilities.py
coolest/template/classes/profile.py
coolest/template/classes/profile_list.py
coolest/template/classes/psf.py
coolest/template/classes/regularization.py
coolest/template/classes/regularization_list.py
coolest/template/classes/util.py
coolest/template/classes/profiles/__init__.py
coolest/template/classes/profiles/light.py
coolest/template/classes/profiles/mass.py
coolest/template/classes/regularizations/__init__.py
coolest/template/classes/regularizations/pixelated.py
coolest-0.1.9.dist-info/AUTHORS.md
coolest-0.1.9.dist-info/LICENSE
coolest-0.1.9.dist-info/METADATA
coolest-0.1.9.dist-info/WHEEL
coolest-0.1.9.dist-info/top_level.txt
coolest-0.1.9.dist-info/RECORD
