Metadata-Version: 2.1
Name: coolest
Version: 0.1.9
Summary: Standard for Strong Gravitational Lensing Analyses
Home-page: https://github.com/aymgal/COOLEST
Download-URL: https://github.com/aymgal/coolest/archive/refs/tags/v0.1.9.tar.gz
Author: Aymeric Galan & COOLEST contributors
Author-email: aymeric.galan@gmail.com
License: GPL-3.0
Project-URL: Documentation, https://coolest.readthedocs.io/
Project-URL: Changelog, https://github.com/aymgal/COOLEST/blob/main/HISTORY.md
Keywords: coolest,lensing,gravitation,astrophysics
Requires-Python: >=3.8
License-File: LICENSE
License-File: AUTHORS.md
Requires-Dist: numpy >=1.20.0
Requires-Dist: scipy >=1.6.3
Requires-Dist: jsonpickle >=2.0.0
Requires-Dist: astropy >=4.2.0
Provides-Extra: opt
Requires-Dist: matplotlib >=3.7.0 ; extra == 'opt'
Requires-Dist: lenstronomy >=1.11.7 ; extra == 'opt'
Requires-Dist: ipython ; extra == 'opt'
Requires-Dist: ipykernel ; extra == 'opt'
Requires-Dist: getdist >=1.3.2 ; extra == 'opt'
